fhir_populator/__init__.py
fhir_populator/__main__.py
fhir_populator/populator.py
fhir_populator/testmain.py
fhir_populator-1.3.0.dist-info/LICENSE
fhir_populator-1.3.0.dist-info/METADATA
fhir_populator-1.3.0.dist-info/WHEEL
fhir_populator-1.3.0.dist-info/top_level.txt
fhir_populator-1.3.0.dist-info/RECORD
