Metadata-Version: 2.1
Name: fhir-populator
Version: 1.3.0
Summary: Load Simplifier packages into a FHIR server, quickly and consistently.
Home-page: https://github.com/itcr-uni-luebeck/fhir-populator
Author: IT Center for Clinical Research, University of Lübeck, Germany
Author-email: j.wiedekopf@uni-luebeck.de
Project-URL: Bug Tracker, https://github.com/itcr-uni-luebeck/fhir-populator/issues
Classifier: Programming Language :: Python :: 3
Classifier: License :: OSI Approved :: BSD License
Classifier: Operating System :: OS Independent
Classifier: Intended Audience :: Healthcare Industry
Classifier: Topic :: Utilities
Requires-Python: >=3.8
License-File: LICENSE
Requires-Dist: requests
Requires-Dist: rich
Requires-Dist: inquirer
Requires-Dist: networkx
Requires-Dist: python-slugify
Requires-Dist: semver
